spinlog/.version
spinlog/__init__.py
spinlog/core.py
spinlog-0.3.0.dist-info/METADATA
spinlog-0.3.0.dist-info/RECORD
spinlog-0.3.0.dist-info/WHEEL
spinlog-0.3.0.dist-info/top_level.txt
