Metadata-Version: 2.1
Name: spinlog
Version: 0.3.0
Summary: Spinner Logger for Python
Home-page: http://github.com/AdrieanKhisbe/spinlog.py
Author: AdrieanKhisbe
Author-email: adriean.khisbe@live.fr
License: UNKNOWN
Keywords: cli terminal log logger logging shell update animation progress
Platform: UNKNOWN
Classifier: Programming Language :: Python
Classifier: Development Status :: 3 - Alpha
Classifier: License :: OSI Approved :: MIT License
Classifier: Natural Language :: English
Classifier: Operating System :: OS Independent
Classifier: Programming Language :: Python :: 3.5
Classifier: Programming Language :: Python :: 3.6
Classifier: Programming Language :: Python :: 3.7
Classifier: Topic :: System :: Logging
Requires-Dist: halo
